{
    "2-25-70": [0, 1, 2, 3, 4, 5, 6, 7, 8, 9, 10, 11, 12, 13, 14, 15, 16, 17, 18, 19, 20, 21, 22, 23, 24, 25, 26, 27, 28, 29, 30, 31, 32, 33, 34, 35, 36, 37, 38, 39, 40, 41, 42, 43, 44, 45, 46, 47, 48, 49, 50, 51, 52, 53, 54, 55, 56, 57, 58, 59, 60, 61, 62, 63],
    "2-25-40": [0, 1, 2, 3, 4, 5, 6, 7, 8, 9, 10, 11, 12, 13, 14, 15, 16, 17, 18, 19, 20, 21, 22, 23, 24, 25, 26, 27, 28, 29, 30, 31, 32, 33, 34, 35, 36, 37, 38, 39, 40, 41, 42, 43, 44, 45, 46, 47, 48, 49, 50, 51, 52, 53, 54, 55, 56, 57, 58, 59, 60, 61, 62, 63],
    "2-25-30": [0, 1, 2, 3, 4, 5, 6, 7, 8, 9, 10, 11, 12, 13, 14, 15, 16, 17, 18, 19, 20, 21, 22, 23, 24, 25, 26, 27, 28, 29, 30, 31, 32, 33, 34, 35, 36, 37, 38, 39, 40, 41, 42, 43, 44, 45, 46, 47, 48, 49, 50, 51, 52, 53, 54, 55, 56, 57, 58, 59, 60, 61, 62, 63],
    "2-25-20": [0, 1, 2, 3, 4, 5, 6, 7, 8, 9, 10, 11, 12, 13, 14, 15, 16, 17, 18, 19, 20, 21, 22, 23, 24, 25, 26, 27, 28, 29, 30, 31, 32, 33, 34, 35, 36, 37, 38, 39, 40, 41, 42, 43, 44, 45, 46, 47, 48, 49, 50, 51, 52, 53, 54, 55, 56, 57, 58, 59, 60, 61, 62, 63],
    "2-29-11": [
        1,
        2,
        3,
        60,
        61,
        62,
        63
    ],
    "2-29-12": [
        1,
        2,
        3,
        60,
        61,
        62,
        63
    ],
    "2-29-13": [
        1,
        2,
        3,
        60,
        61,
        62,
        63
    ],
    "2-29-14": [
        1,
        2,
        3,
        60,
        61,
        62,
        63
    ],
    "2-29-15": [
        1,
        2,
        3,
        60,
        61,
        62,
        63
    ],
    "2-29-16": [
        1,
        2,
        3,
        60,
        61,
        62,
        63
    ],
    "2-29-17": [
        1,
        2,
        3,
        60,
        61,
        62,
        63
    ],
    "2-29-18": [
        1,
        2,
        3,
        60,
        61,
        62,
        63
    ],
    "2-29-19": [
        1,
        2,
        3,
        60,
        61,
        62,
        63
    ],
    "2-29-20": [
        1,
        2,
        3,
        35,
        41,
        45,
        48,
        52,
        53,
        60,
        61,
        62,
        63
    ],
    "2-29-30": [
        35,
        41,
        45,
        48,
        52,
        53,
        60
    ],
    "2-29-40": [
        35,
        41,
        45,
        48,
        52,
        53,
        60
    ],
    "2-29-50": [
        35,
        41,
        45,
        48,
        52,
        53,
        60
    ],
    "2-29-60": [
        35,
        41,
        45,
        48,
        52,
        53,
        60
    ],
    "2-31-70": [
        35,
        41,
        45,
        48,
        52,
        53,
        60
    ],
    "2-31-80": [
        35,
        41,
        45,
        48,
        52,
        53,
        60
    ],
    "2-31-90": [
        35,
        41,
        45,
        48,
        52,
        53,
        60
    ],
    "2-32-100": [
        35,
        41,
        45,
        48,
        52,
        53,
        60
    ],
    "2-32-101": [
        29,
        30,
        31,
        33,
        34,
        35
    ],
    "2-32-102": [
        28,
        29,
        30,
        31,
        33,
        34,
        35
    ],
    "2-32-103": [
        28,
        29,
        30,
        31,
        33,
        34,
        35
    ],
    "2-32-104": [
        28,
        29,
        30,
        31,
        33,
        34,
        35
    ],
    "2-32-105": [
        28,
        29,
        30,
        31,
        33,
        34,
        35
    ],
    "2-32-106": [
        28,
        29,
        30,
        31,
        33,
        34,
        35
    ],
    "2-32-107": [
        28,
        29,
        30,
        31,
        33,
        34,
        35
    ],
    "2-32-108": [
        28,
        29,
        30,
        31,
        33,
        34,
        35
    ],
    "2-32-109": [
        28,
        29,
        30,
        31,
        33,
        34,
        35
    ],
    "2-32-110": [
        28,
        29,
        30,
        31,
        33,
        34,
        35,
        41,
        45,
        48,
        52,
        53,
        60
    ],
    "All": [
        6,
        7,
        8,
        9,
        22,
        23,
        24,
        25,
        38,
        39,
        40,
        54,
        55,
        56,
        57
    ]
}
